README.md
setup.py
nr__train/Binomialdistribution.py
nr__train/Generaldistribution.py
nr__train/Guassiandistribution.py
nr__train/__init__.py
nr_train.egg-info/PKG-INFO
nr_train.egg-info/SOURCES.txt
nr_train.egg-info/dependency_links.txt
nr_train.egg-info/not-zip-safe
nr_train.egg-info/top_level.txt