Metadata-Version: 2.1
Name: nr-train
Version: 0.4
Summary: Gaussian distributions
Home-page: UNKNOWN
Author: Abideen Bello
Author-email: nicholasrichers@gmail.com
License: UNKNOWN
Platform: UNKNOWN
